GalaxyBalaxyUpload/__init__.py
GalaxyBalaxyUpload/config.py
GalaxyBalaxyUpload/main.py
GalaxyBalaxyUpload-1.dist-info/METADATA
GalaxyBalaxyUpload-1.dist-info/WHEEL
GalaxyBalaxyUpload-1.dist-info/entry_points.txt
GalaxyBalaxyUpload-1.dist-info/top_level.txt
GalaxyBalaxyUpload-1.dist-info/RECORD
